run.py
visiofirm/__init__.py
visiofirm/auth_client.py
visiofirm/blindtrust.py
visiofirm/config.py
visiofirm/create_app.py
visiofirm/errortracker.py
visiofirm/exporter.py
visiofirm/imagedownloader.py
visiofirm/imageplot.py
visiofirm/imageremover.py
visiofirm/preannotator.py
visiofirm/projects.py
visiofirm/security.py
visiofirm/tracker.py
visiofirm/models/__init__.py
visiofirm/models/project.py
visiofirm/models/user.py
visiofirm/routes/__init__.py
visiofirm/routes/annotation.py
visiofirm/routes/auth.py
visiofirm/routes/dashboard.py
visiofirm/routes/importer.py
visiofirm/static/css/setup.css
visiofirm/static/css/styles.css
visiofirm/static/img/VisioFirm_logo.png
visiofirm/static/img/bb_logo.gif
visiofirm/static/img/classif_logo.gif
visiofirm/static/img/coco_logo.png
visiofirm/static/img/csv_logo.png
visiofirm/static/img/interpolate_logo.gif
visiofirm/static/img/mask_logo.gif
visiofirm/static/img/mask_video.gif
visiofirm/static/img/obb_logo.gif
visiofirm/static/img/opencv_logo.png
visiofirm/static/img/pascal_voc_logo.png
visiofirm/static/img/sam2_logo.png
visiofirm/static/img/seg_logo.gif
visiofirm/static/img/video_det_logo.gif
visiofirm/static/img/video_seg_logo.gif
visiofirm/static/img/yolo_logo.png
visiofirm/static/img/logos/delete-btn.svg
visiofirm/static/img/logos/duplicate-btn.svg
visiofirm/static/img/logos/grid-btn.svg
visiofirm/static/img/logos/magic-mode.svg
visiofirm/static/img/logos/next-image-btn.svg
visiofirm/static/img/logos/polygon-mode.svg
visiofirm/static/img/logos/prev-image-btn.svg
visiofirm/static/img/logos/rect-mode.svg
visiofirm/static/img/logos/reset-view.svg
visiofirm/static/img/logos/save-btn.svg
visiofirm/static/img/logos/select-mode.svg
visiofirm/static/img/logos/undo-btn.svg
visiofirm/static/img/logos/zoom-in-btn.svg
visiofirm/static/img/logos/zoom-out-btn.svg
visiofirm/static/js/annotationCore.js
visiofirm/static/js/annotationDrawing.js
visiofirm/static/js/annotationInteraction.js
visiofirm/static/js/chunkedUpload.js
visiofirm-1.1.1.dist-info/licenses/LICENSE
visiofirm-1.1.1.dist-info/METADATA
visiofirm-1.1.1.dist-info/WHEEL
visiofirm-1.1.1.dist-info/entry_points.txt
visiofirm-1.1.1.dist-info/top_level.txt
visiofirm-1.1.1.dist-info/RECORD
