Metadata-Version: 2.4
Name: visiofirm
Version: 1.1.1
Summary: Fast almost fully automated image annotation tool for computer vision tasks detection, oriented bounding boxes and segmentation.
Home-page: https://github.com/OschAI/VisioFirm
Author: Safouane El Ghazouali
Author-email: safouane.elghazouali@gmail.com
Classifier: Programming Language :: Python :: 3
Classifier: License :: OSI Approved :: Apache Software License
Classifier: Operating System :: OS Independent
Requires-Python: >=3.10
License-File: LICENSE
Requires-Dist: filelock==3.19.1
Requires-Dist: networkx==3.4.2
Requires-Dist: openai_clip==1.0.1
Requires-Dist: opencv-contrib-python==4.12.0.88
Requires-Dist: Pillow==11.3.0
Requires-Dist: psutil==7.0.0
Requires-Dist: PyYAML==6.0.2
Requires-Dist: rapidfuzz==3.13.0
Requires-Dist: rarfile==4.2
Requires-Dist: torch==2.8.0
Requires-Dist: ultralytics==8.3.185
Requires-Dist: Werkzeug==3.1.3
Requires-Dist: groundingdino-py
Requires-Dist: uvicorn==0.32.0
Requires-Dist: waitress==3.0.2
Requires-Dist: tqdm==4.67.1
Requires-Dist: fastapi==0.115.0
Requires-Dist: python-jose[cryptography]==3.3.0
Requires-Dist: passlib[bcrypt]==1.7.4
Requires-Dist: bcrypt==4.0.1
Requires-Dist: python-multipart==0.0.20
Dynamic: author
Dynamic: author-email
Dynamic: classifier
Dynamic: description
Dynamic: description-content-type
Dynamic: home-page
Dynamic: license-file
Dynamic: requires-dist
Dynamic: requires-python
Dynamic: summary
